IDswapper/__init__.py
IDswapper/data_file.gz
IDswapper/db_config.json
IDswapper/fetchids.py
IDswapper-0.1.8.dist-info/METADATA
IDswapper-0.1.8.dist-info/WHEEL
IDswapper-0.1.8.dist-info/entry_points.txt
IDswapper-0.1.8.dist-info/top_level.txt
IDswapper-0.1.8.dist-info/RECORD
