Metadata-Version: 2.1
Name: IDswapper
Version: 0.1.8
Summary: A tool for swapping IDs in a file by fetching various IDs from idswapper database
Home-page: https://github.com/vkulaganathan/IDswapper/
Author: Pr (France) Dr. rer. nat. Vijay K. ULAGANATHAN
Author-email: 
Classifier: Programming Language :: Python :: 3
Classifier: License :: OSI Approved :: MIT License
Classifier: Operating System :: OS Independent
Requires-Dist: pandas
Requires-Dist: mysql-connector-python
Requires-Dist: tqdm
Requires-Dist: pymysql
